brwording/__init__.py
brwording/brwording.py
brwording/config/cidades.csv
brwording/config/class_words.csv
brwording/config/cloud.jpeg
brwording/config/estados.csv
brwording/config/lematizer.csv
brwording/config/lematizer.txt
brwording/config/negative.csv
brwording/config/nomes.csv
brwording/config/patriarcado-violência.pdf
brwording/config/positive.csv
brwording/config/stopwords.csv
brwording-0.1.2.dist-info/METADATA
brwording-0.1.2.dist-info/WHEEL
brwording-0.1.2.dist-info/top_level.txt
brwording-0.1.2.dist-info/RECORD
