Metadata-Version: 2.1
Name: brwording
Version: 0.1.2
Summary: brwording - Processamento de Linguagem Natural em Português
Home-page: https://github.com/TheScientistBr/BRWording
Author: Delermando Branquinho Filho
Author-email: delermando@gmail.com
License: MIT
Requires-Dist: xlrd (>=2.0.1)
Requires-Dist: openpyxl (>=1.0.1)
Requires-Dist: wordcloud (>=1.8.1)
Requires-Dist: pandas (>=1.2.2)
Requires-Dist: numpy (>=1.19.5)
Requires-Dist: matplotlib (>=3.3.4)
Requires-Dist: pdfminer.six (>=20201018)
Requires-Dist: tqdm (>=4.58.0)
